fake_server.py
fake_server-0.1.dist-info/METADATA
fake_server-0.1.dist-info/WHEEL
fake_server-0.1.dist-info/entry_points.txt
fake_server-0.1.dist-info/top_level.txt
fake_server-0.1.dist-info/RECORD
