Metadata-Version: 2.1
Name: fake-server
Version: 0.1
Summary: A fake server than catch all path and response success message or whatever data you defined.
Home-page: https://github.com/chroming/fake_server
Author: chroming
Author-email: chroming@live.com
License: UNKNOWN
Platform: UNKNOWN
Requires-Dist: click (==7.1.2)
Requires-Dist: flask (==1.1.2)
Requires-Dist: gunicorn
